{
  "href" : "https://pikabu.ru/story/lyubite_svoikh_polovinok_vsegda_ved_kto_znaet_vdrug_i_im_povezet_4923309",
  "id" : 4923309,
  "rating" : 4775,
  "title" : "Любите своих половинок всегда, ведь кто знает вдруг и им повезет",
  "tags" : [ "мемы", "Любовь", "вторая половинка", "деньги" ]
}{
  "href" : "https://pikabu.ru/story/lyubite_svoikh_polovinok_vsegda_ved_kto_znaet_vdrug_i_im_povezet_4923309",
  "id" : 4923309,
  "rating" : 4775,
  "title" : "Любите своих половинок всегда, ведь кто знает вдруг и им повезет",
  "tags" : [ "мемы", "Любовь", "вторая половинка", "деньги" ]
}{
  "href" : "https://pikabu.ru/story/lyubite_svoikh_polovinok_vsegda_ved_kto_znaet_vdrug_i_im_povezet_4923309",
  "id" : 4923309,
  "rating" : 4775,
  "title" : "Любите своих половинок всегда, ведь кто знает вдруг и им повезет",
  "tags" : [ "мемы", "Любовь", "вторая половинка", "деньги" ]
}