{
  "href" : "https://pikabu.ru/story/uk_quotuyutquot_ne_puskaet_sobstvennikov_v_dom_5622763",
  "id" : 5622763,
  "rating" : 5450,
  "title" : "УК \"УЮТ\" не пускает собственников в дом.",
  "tags" : [ "охуевание", "Санкт-Петербург", "нетполитике", "Помощь", "длиннопост" ]
}{
  "href" : "https://pikabu.ru/story/uk_quotuyutquot_ne_puskaet_sobstvennikov_v_dom_5622763",
  "id" : 5622763,
  "rating" : 5450,
  "title" : "УК \"УЮТ\" не пускает собственников в дом.",
  "tags" : [ "охуевание", "Санкт-Петербург", "нетполитике", "Помощь", "длиннопост" ]
}