{
  "href" : "https://pikabu.ru/story/zlo_remney_bezopasnosti_5748420",
  "id" : 5748420,
  "rating" : 12762,
  "title" : "Зло ремней безопасности",
  "tags" : [ "[моё]", "Медицина", "сарказм", "текст", "приемное отделение", "ремень безопасности", "Такси" ]
}{
  "href" : "https://pikabu.ru/story/zlo_remney_bezopasnosti_5748420",
  "id" : 5748420,
  "rating" : 12762,
  "title" : "Зло ремней безопасности",
  "tags" : [ "[моё]", "Медицина", "сарказм", "текст", "приемное отделение", "ремень безопасности", "Такси" ]
}