{
  "href" : "https://pikabu.ru/story/razoblachenie_dorogoy_pikabuproshu_vas_o_pomoshchi_hot_5205507",
  "id" : 5205507,
  "rating" : 18757,
  "title" : "Разоблачение: Дорогой Pikabu,прошу Вас о помощи!!! Hot!!!",
  "tags" : [ "[моё]", "развод", "мошенники", "лига детективов", "Лига юристов", "длиннопост" ]
}{
  "href" : "https://pikabu.ru/story/razoblachenie_dorogoy_pikabuproshu_vas_o_pomoshchi_hot_5205507",
  "id" : 5205507,
  "rating" : 18757,
  "title" : "Разоблачение: Дорогой Pikabu,прошу Вас о помощи!!! Hot!!!",
  "tags" : [ "[моё]", "развод", "мошенники", "лига детективов", "Лига юристов", "длиннопост" ]
}