{
  "href" : "https://pikabu.ru/story/v_svete_poslednikh_sobyitiy_yeto_samyiy_luchshiy_variant_4830277",
  "id" : 4830277,
  "rating" : 8258,
  "title" : "В свете последних событий, это самый лучший вариант",
  "tags" : [ "сычева", "Диана Шурыгина", "изнасилование", "шлюха", "ВКонтакте", "Комментарии" ]
}{
  "href" : "https://pikabu.ru/story/v_svete_poslednikh_sobyitiy_yeto_samyiy_luchshiy_variant_4830277",
  "id" : 4830277,
  "rating" : 8258,
  "title" : "В свете последних событий, это самый лучший вариант",
  "tags" : [ "сычева", "Диана Шурыгина", "изнасилование", "шлюха", "ВКонтакте", "Комментарии" ]
}