{
  "href" : "https://pikabu.ru/story/byit_vzroslyim__prosto_5123046",
  "id" : 5123046,
  "rating" : 7109,
  "title" : "Быть взрослым — просто",
  "tags" : [ "работа", "взрослая жизнь", "Усталость", "перевод", "скриншот" ]
}{
  "href" : "https://pikabu.ru/story/byit_vzroslyim__prosto_5123046",
  "id" : 5123046,
  "rating" : 7109,
  "title" : "Быть взрослым — просто",
  "tags" : [ "работа", "взрослая жизнь", "Усталость", "перевод", "скриншот" ]
}{
  "href" : "https://pikabu.ru/story/byit_vzroslyim__prosto_5123046",
  "id" : 5123046,
  "rating" : 7109,
  "title" : "Быть взрослым — просто",
  "tags" : [ "работа", "взрослая жизнь", "Усталость", "перевод", "скриншот" ]
}