{
  "href" : "https://pikabu.ru/story/inogda_mne_dazhe_nravitsya_ezdit_v_obshchestvennom_transporte_5395124",
  "id" : 5395124,
  "rating" : 120,
  "title" : "Иногда мне даже нравится ездить в общественном транспорте",
  "tags" : [ "грудь", "общественный транспорт" ]
}{
  "href" : "https://pikabu.ru/story/inogda_mne_dazhe_nravitsya_ezdit_v_obshchestvennom_transporte_5395124",
  "id" : 5395124,
  "rating" : 120,
  "title" : "Иногда мне даже нравится ездить в общественном транспорте",
  "tags" : [ "грудь", "общественный транспорт" ]
}