{
  "href" : "https://pikabu.ru/story/stadion_yuventus_vs_stadion_krestovskiy_5038011",
  "id" : 5038011,
  "rating" : 5134,
  "title" : "Стадион Ювентус vs. Стадион Крестовский",
  "tags" : [ "футбол", "стадион", "Крестовский", "Ювентус", "Россия", "Италия" ]
}{
  "href" : "https://pikabu.ru/story/stadion_yuventus_vs_stadion_krestovskiy_5038011",
  "id" : 5038011,
  "rating" : 5134,
  "title" : "Стадион Ювентус vs. Стадион Крестовский",
  "tags" : [ "футбол", "стадион", "Крестовский", "Ювентус", "Россия", "Италия" ]
}