{
  "href" : "https://pikabu.ru/story/quotuchitel_govorit_ya_ne_umeyu_risovat_kotikovquot_5204367",
  "id" : 5204367,
  "rating" : 6487,
  "title" : "\"Учитель говорит, я не умею рисовать котиков\"",
  "tags" : [ "кот", "рисунок", "длиннопост", "не мое" ]
}{
  "href" : "https://pikabu.ru/story/quotuchitel_govorit_ya_ne_umeyu_risovat_kotikovquot_5204367",
  "id" : 5204367,
  "rating" : 6487,
  "title" : "\"Учитель говорит, я не умею рисовать котиков\"",
  "tags" : [ "кот", "рисунок", "длиннопост", "не мое" ]
}